{
  "legislative_session": "2026",
  "identifier": "HB1630",
  "title": "Community Service Revolving Fund; extend repealer on authority to collect fees from paroled offenders for deposit into.",
  "from_organization": "~{\"classification\": \"lower\"}",
  "classification": [
    "bill"
  ],
  "subject": [
    "Corrections"
  ],
  "abstracts": [],
  "other_titles": [],
  "other_identifiers": [
    {
      "identifier": "ocd-bill-ms-2026-hb1630"
    }
  ],
  "actions": [
    {
      "description": "Referred To Corrections",
      "date": "2026-01-19T06:00:00+00:00",
      "organization_id": "~{\"classification\": \"lower\"}",
      "classification": [
        "referral-committee"
      ],
      "related_entities": [],
      "_processing": {
        "log_file_created": "2026-07-13T06:03:59Z"
      }
    },
    {
      "description": "Title Suff Do Pass",
      "date": "2026-02-02T06:00:00+00:00",
      "organization_id": "~{\"classification\": \"lower\"}",
      "classification": [
        "committee-passage"
      ],
      "related_entities": [],
      "_processing": {
        "log_file_created": "2026-07-13T06:03:59Z"
      }
    },
    {
      "description": "Passed",
      "date": "2026-02-10T06:00:00+00:00",
      "organization_id": "~{\"classification\": \"lower\"}",
      "classification": [
        "passage"
      ],
      "related_entities": [],
      "_processing": {
        "log_file_created": "2026-07-15T13:02:28Z"
      }
    },
    {
      "description": "Transmitted To Senate",
      "date": "2026-02-11T06:00:00+00:00",
      "organization_id": "~{\"classification\": \"lower\"}",
      "classification": [
        "introduction"
      ],
      "related_entities": [],
      "_processing": {
        "log_file_created": "2026-07-15T13:02:28Z"
      }
    },
    {
      "description": "Referred To Corrections",
      "date": "2026-02-17T06:00:00+00:00",
      "organization_id": "~{\"classification\": \"upper\"}",
      "classification": [
        "referral-committee"
      ],
      "related_entities": [],
      "_processing": {
        "log_file_created": "2026-07-15T13:02:28Z"
      }
    },
    {
      "description": "Died In Committee",
      "date": "2026-03-03T06:00:00+00:00",
      "organization_id": "~{\"classification\": \"upper\"}",
      "classification": [],
      "related_entities": [],
      "_processing": {
        "log_file_created": "2026-07-15T13:02:28Z"
      }
    }
  ],
  "sponsorships": [
    {
      "name": "Shanks",
      "classification": "primary",
      "entity_type": "person",
      "primary": true,
      "person_id": "~{\"name\": \"Shanks\"}",
      "organization_id": null
    }
  ],
  "related_bills": [],
  "versions": [
    {
      "note": "Current version",
      "links": [
        {
          "url": "http://billstatus.ls.state.ms.us/documents/2026/html/HB/1600-1699/HB1630PS.htm",
          "media_type": "text/html"
        },
        {
          "url": "http://billstatus.ls.state.ms.us/documents/2026/pdf/HB/1600-1699/HB1630PS.pdf",
          "media_type": "application/pdf"
        }
      ],
      "date": "",
      "classification": ""
    },
    {
      "note": "As Introduced",
      "links": [
        {
          "url": "http://billstatus.ls.state.ms.us/documents/2026/html/HB/1600-1699/HB1630IN.htm",
          "media_type": "text/html"
        },
        {
          "url": "http://billstatus.ls.state.ms.us/documents/2026/pdf/HB/1600-1699/HB1630IN.pdf",
          "media_type": "application/pdf"
        }
      ],
      "date": "",
      "classification": ""
    }
  ],
  "documents": [],
  "citations": [],
  "sources": [
    {
      "url": "https://billstatus.ls.state.ms.us/documents/2026/pdf/HB/1600-1699/HB1630PS.pdf",
      "note": ""
    },
    {
      "url": "http://billstatus.ls.state.ms.us/2026/pdf/House_authors/Shanks.xml",
      "note": ""
    },
    {
      "url": "https://billstatus.ls.state.ms.us/2026/pdf/history/HB/HB1630.xml",
      "note": ""
    }
  ],
  "extras": {
    "summary": "AN ACT TO AMEND SECTION 47-7-49, MISSISSIPPI CODE OF 1972, TO EXTEND THE DATE OF THE REPEALER ON THE AUTHORITY OF THE MISSISSIPPI DEPARTMENT OF CORRECTIONS TO COLLECT MONTHLY FEES FROM OFFENDERS WHO ARE ON PROBATION, PAROLE OR ANY OTHER FIELD SUPERVISION AND TO DEPOSIT THOSE FEES INTO THE COMMUNITY SERVICE REVOLVING FUND; AND FOR RELATED PURPOSES."
  },
  "jurisdiction": {
    "id": "ocd-jurisdiction/country:us/state:ms/government",
    "name": "Mississippi",
    "classification": "state",
    "division_id": "ocd-division/country:us/state:ms"
  },
  "_processing": {
    "logs_latest_update": "2026-07-15T13:02:28Z",
    "text_extraction_latest_update": "2026-07-13T07:45:54.883461Z"
  }
}