{
  "legislative_session": "2026",
  "identifier": "HB1439",
  "title": "Health Dept and Bd of Medical Licensure; Governor shall select private auditor to determine their compliance with certain laws.",
  "from_organization": "~{\"classification\": \"lower\"}",
  "classification": [
    "bill"
  ],
  "subject": [
    "Accountability, Efficiency, Transparency"
  ],
  "abstracts": [],
  "other_titles": [],
  "other_identifiers": [
    {
      "identifier": "ocd-bill-ms-2026-hb1439"
    }
  ],
  "actions": [
    {
      "description": "Referred To Accountability, Efficiency, Transparency",
      "date": "2026-01-16T06:00:00+00:00",
      "organization_id": "~{\"classification\": \"lower\"}",
      "classification": [
        "referral-committee"
      ],
      "related_entities": [],
      "_processing": {
        "log_file_created": "2026-07-13T06:03:59Z"
      }
    },
    {
      "description": "Died In Committee",
      "date": "2026-02-03T06:00:00+00:00",
      "organization_id": "~{\"classification\": \"lower\"}",
      "classification": [],
      "related_entities": [],
      "_processing": {
        "log_file_created": "2026-07-13T06:03:59Z"
      }
    }
  ],
  "sponsorships": [
    {
      "name": "Eubanks",
      "classification": "primary",
      "entity_type": "person",
      "primary": true,
      "person_id": "~{\"name\": \"Eubanks\"}",
      "organization_id": null
    }
  ],
  "related_bills": [],
  "versions": [
    {
      "note": "Current version",
      "links": [
        {
          "url": "http://billstatus.ls.state.ms.us/documents/2026/html/HB/1400-1499/HB1439IN.htm",
          "media_type": "text/html"
        },
        {
          "url": "http://billstatus.ls.state.ms.us/documents/2026/pdf/HB/1400-1499/HB1439IN.pdf",
          "media_type": "application/pdf"
        }
      ],
      "date": "",
      "classification": ""
    }
  ],
  "documents": [],
  "citations": [],
  "sources": [
    {
      "url": "https://billstatus.ls.state.ms.us/documents/2026/pdf/HB/1400-1499/HB1439IN.pdf",
      "note": ""
    },
    {
      "url": "http://billstatus.ls.state.ms.us/2026/pdf/House_authors/Eubanks.xml",
      "note": ""
    },
    {
      "url": "https://billstatus.ls.state.ms.us/2026/pdf/history/HB/HB1439.xml",
      "note": ""
    }
  ],
  "extras": {
    "summary": "AN ACT TO DIRECT THE GOVERNOR TO SELECT A PRIVATE AUDITOR TO PERFORM AN AUDIT OF THE STATE DEPARTMENT OF HEALTH AND THE STATE BOARD OF MEDICAL LICENSURE TO DETERMINE THE AGENCIES' COMPLIANCE WITH CERTAIN LAWS; TO REQUIRE THE PRIVATE AUDITOR TO PROVIDE A REPORT TO THE GOVERNOR, LIEUTENANT GOVERNOR, AND SPEAKER OF THE HOUSE OF REPRESENTATIVES DETAILING THE FINDINGS OF THE AUDIT REQUIRED BY THIS ACT; AND FOR RELATED PURPOSES."
  },
  "jurisdiction": {
    "id": "ocd-jurisdiction/country:us/state:ms/government",
    "name": "Mississippi",
    "classification": "state",
    "division_id": "ocd-division/country:us/state:ms"
  },
  "_processing": {
    "logs_latest_update": "2026-07-13T06:03:59Z"
  }
}