{
  "legislative_session": "2026",
  "identifier": "SN78",
  "title": "Vaiden Arthur Clark, Jackson, Mississippi, Board of Directors of the College Savings Plan of Mississippi to represent the Fourth Congressional District, five year term effective July 1, 2025 and ending June 30, 2030.",
  "from_organization": "~{\"classification\": \"upper\"}",
  "classification": [
    "nomination"
  ],
  "subject": [
    "Universities and Colleges"
  ],
  "abstracts": [],
  "other_titles": [],
  "other_identifiers": [
    {
      "identifier": "ocd-bill-ms-2026-sn78"
    }
  ],
  "actions": [
    {
      "description": "Referred To Universities and Colleges",
      "date": "2026-01-19T06:00:00+00:00",
      "organization_id": "~{\"classification\": \"upper\"}",
      "classification": [
        "referral-committee"
      ],
      "related_entities": [],
      "_processing": {
        "log_file_created": "2026-07-13T06:03:59Z"
      }
    },
    {
      "description": "Died In Committee",
      "date": "2026-04-15T05:00:00+00:00",
      "organization_id": "~{\"classification\": \"upper\"}",
      "classification": [],
      "related_entities": [],
      "_processing": {
        "log_file_created": "2026-07-15T13:02:29Z"
      }
    },
    {
      "description": "Notified of Return",
      "date": "2026-04-16T05:00:00+00:00",
      "organization_id": "~{\"classification\": \"upper\"}",
      "classification": [],
      "related_entities": [],
      "_processing": {
        "log_file_created": "2026-07-15T13:02:29Z"
      }
    }
  ],
  "sponsorships": [
    {
      "name": "GOVERNOR",
      "classification": "primary",
      "entity_type": "person",
      "primary": true,
      "person_id": "~{\"name\": \"GOVERNOR\"}",
      "organization_id": null
    }
  ],
  "related_bills": [],
  "versions": [],
  "documents": [],
  "citations": [],
  "sources": [
    {
      "url": "https://billstatus.ls.state.ms.us/",
      "note": ""
    },
    {
      "url": "http://billstatus.ls.state.ms.us/2026/pdf/",
      "note": ""
    },
    {
      "url": "https://billstatus.ls.state.ms.us/2026/pdf/history/SN/SN0078.xml",
      "note": ""
    }
  ],
  "extras": {
    "summary": ""
  },
  "jurisdiction": {
    "id": "ocd-jurisdiction/country:us/state:ms/government",
    "name": "Mississippi",
    "classification": "state",
    "division_id": "ocd-division/country:us/state:ms"
  },
  "_processing": {
    "logs_latest_update": "2026-07-15T13:02:29Z",
    "text_extraction_latest_update": "2026-07-15T10:04:38.536564Z"
  }
}