{
  "legislative_session": "2026",
  "identifier": "SB2409",
  "title": "Mississippi Department of Insurance; establish comprehensive mitigation program for retrofitting insurable homes.",
  "from_organization": "~{\"classification\": \"upper\"}",
  "classification": [
    "bill"
  ],
  "subject": [
    "Accountability, Efficiency, Transparency",
    "Insurance"
  ],
  "abstracts": [],
  "other_titles": [],
  "other_identifiers": [
    {
      "identifier": "ocd-bill-ms-2026-sb2409"
    }
  ],
  "actions": [
    {
      "description": "Referred To Insurance",
      "date": "2026-01-19T06:00:00+00:00",
      "organization_id": "~{\"classification\": \"upper\"}",
      "classification": [
        "referral-committee"
      ],
      "related_entities": [],
      "_processing": {
        "log_file_created": "2026-07-13T06:03:59Z"
      }
    },
    {
      "description": "Title Suff Do Pass",
      "date": "2026-02-03T06:00:00+00:00",
      "organization_id": "~{\"classification\": \"upper\"}",
      "classification": [
        "committee-passage"
      ],
      "related_entities": [],
      "_processing": {
        "log_file_created": "2026-07-13T06:03:59Z"
      }
    },
    {
      "description": "Passed",
      "date": "2026-02-10T06:00:00+00:00",
      "organization_id": "~{\"classification\": \"upper\"}",
      "classification": [
        "passage"
      ],
      "related_entities": [],
      "_processing": {
        "log_file_created": "2026-07-15T13:02:31Z"
      }
    },
    {
      "description": "Transmitted To House",
      "date": "2026-02-11T06:00:00+00:00",
      "organization_id": "~{\"classification\": \"upper\"}",
      "classification": [
        "introduction"
      ],
      "related_entities": [],
      "_processing": {
        "log_file_created": "2026-07-15T13:02:31Z"
      }
    },
    {
      "description": "Referred To Insurance;Accountability, Efficiency, Transparency",
      "date": "2026-02-13T06:00:00+00:00",
      "organization_id": "~{\"classification\": \"lower\"}",
      "classification": [
        "referral-committee"
      ],
      "related_entities": [],
      "_processing": {
        "log_file_created": "2026-07-15T13:02:31Z"
      }
    },
    {
      "description": "DR - TSDPAA: IN To AC",
      "date": "2026-03-03T06:00:00+00:00",
      "organization_id": "~{\"classification\": \"lower\"}",
      "classification": [],
      "related_entities": [],
      "_processing": {
        "log_file_created": "2026-07-15T13:02:31Z"
      }
    },
    {
      "description": "DR - TSDPAA: AC To IN",
      "date": "2026-03-03T06:00:00+00:00",
      "organization_id": "~{\"classification\": \"lower\"}",
      "classification": [],
      "related_entities": [],
      "_processing": {
        "log_file_created": "2026-07-15T13:02:31Z"
      }
    },
    {
      "description": "Title Suff Do Pass As Amended",
      "date": "2026-03-03T06:00:00+00:00",
      "organization_id": "~{\"classification\": \"lower\"}",
      "classification": [
        "committee-passage"
      ],
      "related_entities": [],
      "_processing": {
        "log_file_created": "2026-07-15T13:02:31Z"
      }
    },
    {
      "description": "Amended",
      "date": "2026-03-04T06:00:00+00:00",
      "organization_id": "~{\"classification\": \"lower\"}",
      "classification": [
        "amendment-passage"
      ],
      "related_entities": [],
      "_processing": {
        "log_file_created": "2026-07-15T13:02:31Z"
      }
    },
    {
      "description": "Passed As Amended",
      "date": "2026-03-04T06:00:00+00:00",
      "organization_id": "~{\"classification\": \"lower\"}",
      "classification": [
        "passage"
      ],
      "related_entities": [],
      "_processing": {
        "log_file_created": "2026-07-15T13:02:31Z"
      }
    },
    {
      "description": "Returned For Concurrence",
      "date": "2026-03-05T06:00:00+00:00",
      "organization_id": "~{\"classification\": \"lower\"}",
      "classification": [],
      "related_entities": [],
      "_processing": {
        "log_file_created": "2026-07-15T13:02:31Z"
      }
    },
    {
      "description": "Decline to Concur/Invite Conf",
      "date": "2026-03-11T05:00:00+00:00",
      "organization_id": "~{\"classification\": \"upper\"}",
      "classification": [],
      "related_entities": [],
      "_processing": {
        "log_file_created": "2026-07-15T13:02:31Z"
      }
    },
    {
      "description": "Conferees Named Michel,DeLano,Kirby",
      "date": "2026-03-17T05:00:00+00:00",
      "organization_id": "~{\"classification\": \"upper\"}",
      "classification": [],
      "related_entities": [],
      "_processing": {
        "log_file_created": "2026-07-15T13:02:31Z"
      }
    },
    {
      "description": "Conferees Named Turner,Ford (54th),Zuber",
      "date": "2026-03-19T05:00:00+00:00",
      "organization_id": "~{\"classification\": \"lower\"}",
      "classification": [],
      "related_entities": [],
      "_processing": {
        "log_file_created": "2026-07-15T13:02:31Z"
      }
    },
    {
      "description": "Conference Report Filed",
      "date": "2026-03-30T05:00:00+00:00",
      "organization_id": "~{\"classification\": \"upper\"}",
      "classification": [],
      "related_entities": [],
      "_processing": {
        "log_file_created": "2026-07-15T13:02:31Z"
      }
    },
    {
      "description": "Conference Report Filed",
      "date": "2026-03-30T05:00:00+00:00",
      "organization_id": "~{\"classification\": \"lower\"}",
      "classification": [],
      "related_entities": [],
      "_processing": {
        "log_file_created": "2026-07-15T13:02:31Z"
      }
    },
    {
      "description": "Recommitted For Further Conf",
      "date": "2026-03-31T05:00:00+00:00",
      "organization_id": "~{\"classification\": \"upper\"}",
      "classification": [],
      "related_entities": [],
      "_processing": {
        "log_file_created": "2026-07-15T13:02:31Z"
      }
    },
    {
      "description": "Recommitted For Further Conf",
      "date": "2026-03-31T05:00:00+00:00",
      "organization_id": "~{\"classification\": \"lower\"}",
      "classification": [],
      "related_entities": [],
      "_processing": {
        "log_file_created": "2026-07-15T13:02:31Z"
      }
    },
    {
      "description": "Conference Report Filed",
      "date": "2026-03-31T05:00:00+00:00",
      "organization_id": "~{\"classification\": \"lower\"}",
      "classification": [],
      "related_entities": [],
      "_processing": {
        "log_file_created": "2026-07-15T13:02:31Z"
      }
    },
    {
      "description": "Conference Report Filed",
      "date": "2026-03-31T05:00:00+00:00",
      "organization_id": "~{\"classification\": \"upper\"}",
      "classification": [],
      "related_entities": [],
      "_processing": {
        "log_file_created": "2026-07-15T13:02:31Z"
      }
    },
    {
      "description": "Unanimous Consent Granted",
      "date": "2026-04-01T05:00:00+00:00",
      "organization_id": "~{\"classification\": \"lower\"}",
      "classification": [],
      "related_entities": [],
      "_processing": {
        "log_file_created": "2026-07-15T13:02:31Z"
      }
    },
    {
      "description": "Conference Report Adopted",
      "date": "2026-04-01T05:00:00+00:00",
      "organization_id": "~{\"classification\": \"lower\"}",
      "classification": [],
      "related_entities": [],
      "_processing": {
        "log_file_created": "2026-07-15T13:02:31Z"
      }
    },
    {
      "description": "Conference Report Adopted",
      "date": "2026-04-01T05:00:00+00:00",
      "organization_id": "~{\"classification\": \"upper\"}",
      "classification": [],
      "related_entities": [],
      "_processing": {
        "log_file_created": "2026-07-15T13:02:31Z"
      }
    },
    {
      "description": "Unanimous Consent Granted",
      "date": "2026-04-01T05:00:00+00:00",
      "organization_id": "~{\"classification\": \"upper\"}",
      "classification": [],
      "related_entities": [],
      "_processing": {
        "log_file_created": "2026-07-15T13:02:31Z"
      }
    },
    {
      "description": "Enrolled Bill Signed",
      "date": "2026-04-06T05:00:00+00:00",
      "organization_id": "~{\"classification\": \"upper\"}",
      "classification": [],
      "related_entities": [],
      "_processing": {
        "log_file_created": "2026-07-15T13:02:31Z"
      }
    },
    {
      "description": "Enrolled Bill Signed",
      "date": "2026-04-06T05:00:00+00:00",
      "organization_id": "~{\"classification\": \"lower\"}",
      "classification": [],
      "related_entities": [],
      "_processing": {
        "log_file_created": "2026-07-15T13:02:31Z"
      }
    },
    {
      "description": "Approved by Governor",
      "date": "2026-04-09T05:00:00+00:00",
      "organization_id": "~{\"classification\": \"executive\"}",
      "classification": [
        "executive-signature"
      ],
      "related_entities": [],
      "_processing": {
        "log_file_created": "2026-07-15T13:02:31Z"
      }
    }
  ],
  "sponsorships": [
    {
      "name": "Michel",
      "classification": "primary",
      "entity_type": "person",
      "primary": true,
      "person_id": "~{\"name\": \"Michel\"}",
      "organization_id": null
    },
    {
      "name": "Kirby",
      "classification": "cosponsor",
      "entity_type": "person",
      "primary": false,
      "person_id": "~{\"name\": \"Kirby\"}",
      "organization_id": null
    },
    {
      "name": "DeLano",
      "classification": "cosponsor",
      "entity_type": "person",
      "primary": false,
      "person_id": "~{\"name\": \"DeLano\"}",
      "organization_id": null
    },
    {
      "name": "Seymour",
      "classification": "cosponsor",
      "entity_type": "person",
      "primary": false,
      "person_id": "~{\"name\": \"Seymour\"}",
      "organization_id": null
    },
    {
      "name": "Younger",
      "classification": "cosponsor",
      "entity_type": "person",
      "primary": false,
      "person_id": "~{\"name\": \"Younger\"}",
      "organization_id": null
    },
    {
      "name": "Carter",
      "classification": "cosponsor",
      "entity_type": "person",
      "primary": false,
      "person_id": "~{\"name\": \"Carter\"}",
      "organization_id": null
    },
    {
      "name": "England",
      "classification": "cosponsor",
      "entity_type": "person",
      "primary": false,
      "person_id": "~{\"name\": \"England\"}",
      "organization_id": null
    },
    {
      "name": "Thompson",
      "classification": "cosponsor",
      "entity_type": "person",
      "primary": false,
      "person_id": "~{\"name\": \"Thompson\"}",
      "organization_id": null
    }
  ],
  "related_bills": [],
  "versions": [
    {
      "note": "Current version",
      "links": [
        {
          "url": "http://billstatus.ls.state.ms.us/documents/2026/html/SB/2400-2499/SB2409SG.htm",
          "media_type": "text/html"
        },
        {
          "url": "http://billstatus.ls.state.ms.us/documents/2026/pdf/SB/2400-2499/SB2409SG.pdf",
          "media_type": "application/pdf"
        }
      ],
      "date": "",
      "classification": ""
    },
    {
      "note": "As Introduced",
      "links": [
        {
          "url": "http://billstatus.ls.state.ms.us/documents/2026/html/SB/2400-2499/SB2409IN.htm",
          "media_type": "text/html"
        },
        {
          "url": "http://billstatus.ls.state.ms.us/documents/2026/pdf/SB/2400-2499/SB2409IN.pdf",
          "media_type": "application/pdf"
        }
      ],
      "date": "",
      "classification": ""
    },
    {
      "note": "As Passed the upper",
      "links": [
        {
          "url": "http://billstatus.ls.state.ms.us/documents/2026/html/SB/2400-2499/SB2409PS.htm",
          "media_type": "text/html"
        },
        {
          "url": "http://billstatus.ls.state.ms.us/documents/2026/pdf/SB/2400-2499/SB2409PS.pdf",
          "media_type": "application/pdf"
        }
      ],
      "date": "",
      "classification": ""
    },
    {
      "note": "Amendment Report for Senate Bill No. 2409",
      "links": [
        {
          "url": "http://billstatus.ls.state.ms.us/documents/2026/pdf/ham/Amendment_Report_for_SB2409.pdf",
          "media_type": "application/pdf"
        },
        {
          "url": "http://billstatus.ls.state.ms.us/documents/2026/html/ham/Amendment_Report_for_SB2409.htm",
          "media_type": "text/html"
        }
      ],
      "date": "",
      "classification": ""
    },
    {
      "note": "Committee Amendment No 1 (Adopted) (Voice Vote)",
      "links": [
        {
          "url": "http://billstatus.ls.state.ms.us/documents/2026/pdf/ham/SB2409_H_Cmte_Amend_01.pdf",
          "media_type": "application/pdf"
        },
        {
          "url": "http://billstatus.ls.state.ms.us/documents/2026/html/ham/SB2409_H_Cmte_Amend_01.htm",
          "media_type": "text/html"
        }
      ],
      "date": "",
      "classification": ""
    }
  ],
  "documents": [],
  "citations": [],
  "sources": [
    {
      "url": "https://billstatus.ls.state.ms.us/documents/2026/pdf/SB/2400-2499/SB2409SG.pdf",
      "note": ""
    },
    {
      "url": "http://billstatus.ls.state.ms.us/2026/pdf/Senate_authors/Michel.xml",
      "note": ""
    },
    {
      "url": "http://billstatus.ls.state.ms.us/2026/pdf/House_authors/Kirby.xml",
      "note": ""
    },
    {
      "url": "http://billstatus.ls.state.ms.us/2026/pdf/House_authors/DeLano.xml",
      "note": ""
    },
    {
      "url": "http://billstatus.ls.state.ms.us/2026/pdf/House_authors/Seymour.xml",
      "note": ""
    },
    {
      "url": "http://billstatus.ls.state.ms.us/2026/pdf/House_authors/Younger.xml",
      "note": ""
    },
    {
      "url": "http://billstatus.ls.state.ms.us/2026/pdf/House_authors/Carter.xml",
      "note": ""
    },
    {
      "url": "http://billstatus.ls.state.ms.us/2026/pdf/House_authors/England.xml",
      "note": ""
    },
    {
      "url": "http://billstatus.ls.state.ms.us/2026/pdf/House_authors/Thompson.xml",
      "note": ""
    },
    {
      "url": "https://billstatus.ls.state.ms.us/2026/pdf/history/SB/SB2409.xml",
      "note": ""
    }
  ],
  "extras": {
    "summary": "AN ACT TO CREATE THE \"STRENGTHEN MISSISSIPPI HOMES ACT\" TO ESTABLISH A COMPREHENSIVE MITIGATION PROGRAM IN THE MISSISSIPPI DEPARTMENT OF INSURANCE FOR RETROFITTING INSURABLE HOMES; TO AMEND SECTION 83-1-191, MISSISSIPPI CODE OF 1972, TO RENAME THE \"COMPREHENSIVE HURRICANE DAMAGE MITIGATION PROGRAM\" TO THE \"STRENGTHEN MISSISSIPPI HOMES PROGRAM\"; TO ESTABLISH CRITERIA FOR THE NEW PROGRAM; TO INCLUDE HURRICANE, TORNADO, HAIL, OR OTHER CATASTROPHIC WINDSTORM EVENT MITIGATION; TO ESTABLISH AN ADVISORY COUNCIL; TO PROVIDE FOR OPERATIONAL REPORTS TO BE SUBMITTED TO THE GOVERNOR AND THE LEGISLATURE; TO INCREASE THE AMOUNTS OF FINANCIAL GRANTS OFFERED BY THE STRENGTHEN MISSISSIPPI HOMES PROGRAM TO $10,000.00 PER HOME AND TO ALLOW THE MISSISSIPPI DEPARTMENT OF INSURANCE TO ESTABLISH CRITERIA FOR THE ISSUING OF GRANTS BY REGULATION; TO PROVIDE THAT GRANTS SHALL BE SUBJECT TO APPROPRIATION; TO RENAME THE \"COMPREHENSIVE HURRICANE DAMAGE MITIGATION PROGRAM FUND\" TO THE \"STRENGTHEN MISSISSIPPI HOMES FUND\"; TO REMOVE THE REPEALER; TO AMEND SECTION 83-5-73, MISSISSIPPI CODE OF 1972, TO INCREASE THE FEE CHARGED FOR AN AGENT'S CERTIFICATE OF AUTHORITY; AND FOR OTHER RELATED PURPOSES."
  },
  "jurisdiction": {
    "id": "ocd-jurisdiction/country:us/state:ms/government",
    "name": "Mississippi",
    "classification": "state",
    "division_id": "ocd-division/country:us/state:ms"
  },
  "_processing": {
    "logs_latest_update": "2026-07-15T13:02:31Z",
    "text_extraction_latest_update": "2026-07-15T18:03:11.514791Z"
  }
}