{
  "legislative_session": "2026",
  "identifier": "HB409",
  "title": "Medicaid; expand eligibility under federal Affordable Care Act.",
  "from_organization": "~{\"classification\": \"lower\"}",
  "classification": [
    "bill"
  ],
  "subject": [
    "Appropriations A",
    "Medicaid"
  ],
  "abstracts": [],
  "other_titles": [],
  "other_identifiers": [
    {
      "identifier": "ocd-bill-ms-2026-hb409"
    }
  ],
  "actions": [
    {
      "description": "Referred To Medicaid;Appropriations A",
      "date": "2026-01-12T06:00:00+00:00",
      "organization_id": "~{\"classification\": \"lower\"}",
      "classification": [
        "referral-committee"
      ],
      "related_entities": [],
      "_processing": {
        "log_file_created": "2026-07-13T06:03:59Z"
      }
    },
    {
      "description": "Died In Committee",
      "date": "2026-02-03T06:00:00+00:00",
      "organization_id": "~{\"classification\": \"lower\"}",
      "classification": [],
      "related_entities": [],
      "_processing": {
        "log_file_created": "2026-07-13T06:03:59Z"
      }
    }
  ],
  "sponsorships": [
    {
      "name": "Karriem",
      "classification": "primary",
      "entity_type": "person",
      "primary": true,
      "person_id": "~{\"name\": \"Karriem\"}",
      "organization_id": null
    }
  ],
  "related_bills": [],
  "versions": [
    {
      "note": "Current version",
      "links": [
        {
          "url": "http://billstatus.ls.state.ms.us/documents/2026/html/HB/0400-0499/HB0409IN.htm",
          "media_type": "text/html"
        },
        {
          "url": "http://billstatus.ls.state.ms.us/documents/2026/pdf/HB/0400-0499/HB0409IN.pdf",
          "media_type": "application/pdf"
        }
      ],
      "date": "",
      "classification": ""
    }
  ],
  "documents": [],
  "citations": [],
  "sources": [
    {
      "url": "https://billstatus.ls.state.ms.us/documents/2026/pdf/HB/0400-0499/HB0409IN.pdf",
      "note": ""
    },
    {
      "url": "http://billstatus.ls.state.ms.us/2026/pdf/House_authors/Karriem.xml",
      "note": ""
    },
    {
      "url": "https://billstatus.ls.state.ms.us/2026/pdf/history/HB/HB0409.xml",
      "note": ""
    }
  ],
  "extras": {
    "summary": "AN ACT TO AMEND SECTION 43-13-115, MISSISSIPPI CODE OF 1972, TO PROVIDE MEDICAID COVERAGE FOR INDIVIDUALS WHO ARE UNDER 65 YEARS OF AGE, ARE NOT PREGNANT, ARE NOT ENTITLED TO OR ENROLLED FOR MEDICARE BENEFITS AND WHOSE INCOME IS NOT MORE THAN 133% OF THE FEDERAL POVERTY LEVEL, AS AUTHORIZED UNDER THE FEDERAL PATIENT PROTECTION AND AFFORDABLE CARE ACT; AND FOR RELATED PURPOSES."
  },
  "jurisdiction": {
    "id": "ocd-jurisdiction/country:us/state:ms/government",
    "name": "Mississippi",
    "classification": "state",
    "division_id": "ocd-division/country:us/state:ms"
  },
  "_processing": {
    "logs_latest_update": "2026-07-13T06:03:59Z",
    "text_extraction_latest_update": "2026-07-13T06:43:12.975811Z"
  }
}