{
  "legislative_session": "2026",
  "identifier": "SB2109",
  "title": "License plates; prohibit equipping of device that hides or obscures.",
  "from_organization": "~{\"classification\": \"upper\"}",
  "classification": [
    "bill"
  ],
  "subject": [
    "Judiciary, Division B"
  ],
  "abstracts": [],
  "other_titles": [],
  "other_identifiers": [
    {
      "identifier": "ocd-bill-ms-2026-sb2109"
    }
  ],
  "actions": [
    {
      "description": "Referred To Judiciary, Division B",
      "date": "2026-01-09T06:00:00+00:00",
      "organization_id": "~{\"classification\": \"upper\"}",
      "classification": [
        "referral-committee"
      ],
      "related_entities": [],
      "_processing": {
        "log_file_created": "2026-07-13T06:03:59Z"
      }
    },
    {
      "description": "Died In Committee",
      "date": "2026-02-03T06:00:00+00:00",
      "organization_id": "~{\"classification\": \"upper\"}",
      "classification": [],
      "related_entities": [],
      "_processing": {
        "log_file_created": "2026-07-13T06:03:59Z"
      }
    }
  ],
  "sponsorships": [
    {
      "name": "Fillingane",
      "classification": "primary",
      "entity_type": "person",
      "primary": true,
      "person_id": "~{\"name\": \"Fillingane\"}",
      "organization_id": null
    }
  ],
  "related_bills": [],
  "versions": [
    {
      "note": "Current version",
      "links": [
        {
          "url": "http://billstatus.ls.state.ms.us/documents/2026/html/SB/2100-2199/SB2109IN.htm",
          "media_type": "text/html"
        },
        {
          "url": "http://billstatus.ls.state.ms.us/documents/2026/pdf/SB/2100-2199/SB2109IN.pdf",
          "media_type": "application/pdf"
        }
      ],
      "date": "",
      "classification": ""
    }
  ],
  "documents": [],
  "citations": [],
  "sources": [
    {
      "url": "https://billstatus.ls.state.ms.us/documents/2026/pdf/SB/2100-2199/SB2109IN.pdf",
      "note": ""
    },
    {
      "url": "http://billstatus.ls.state.ms.us/2026/pdf/Senate_authors/Fillingane.xml",
      "note": ""
    },
    {
      "url": "https://billstatus.ls.state.ms.us/2026/pdf/history/SB/SB2109.xml",
      "note": ""
    }
  ],
  "extras": {
    "summary": "AN ACT TO AMEND SECTION 27-19-31, MISSISSIPPI CODE OF 1972, TO PROHIBIT THE EQUIPPING OF A MANUAL, ELECTRONIC OR MECHANICAL DEVICE THAT HIDES OR OBSCURES A LICENSE PLATE; TO BRING FORWARD SECTION 27-19-131, MISSISSIPPI CODE OF 1972, FOR POSSIBLE AMENDMENT; AND FOR RELATED PURPOSES."
  },
  "jurisdiction": {
    "id": "ocd-jurisdiction/country:us/state:ms/government",
    "name": "Mississippi",
    "classification": "state",
    "division_id": "ocd-division/country:us/state:ms"
  },
  "_processing": {
    "logs_latest_update": "2026-07-13T06:03:59Z"
  }
}