{
  "legislative_session": "2026",
  "identifier": "HB1418",
  "title": "Medicaid; provide for reimbursement for vagus nerve stimulation (VNS) surgical implant procedures.",
  "from_organization": "~{\"classification\": \"lower\"}",
  "classification": [
    "bill"
  ],
  "subject": [
    "Appropriations A",
    "Medicaid"
  ],
  "abstracts": [],
  "other_titles": [],
  "other_identifiers": [
    {
      "identifier": "ocd-bill-ms-2026-hb1418"
    }
  ],
  "actions": [
    {
      "description": "Referred To Medicaid;Appropriations A",
      "date": "2026-01-16T06:00:00+00:00",
      "organization_id": "~{\"classification\": \"lower\"}",
      "classification": [
        "referral-committee"
      ],
      "related_entities": [],
      "_processing": {
        "log_file_created": "2026-07-13T06:03:59Z"
      }
    },
    {
      "description": "Died In Committee",
      "date": "2026-02-03T06:00:00+00:00",
      "organization_id": "~{\"classification\": \"lower\"}",
      "classification": [],
      "related_entities": [],
      "_processing": {
        "log_file_created": "2026-07-13T06:03:59Z"
      }
    }
  ],
  "sponsorships": [
    {
      "name": "Mansell",
      "classification": "primary",
      "entity_type": "person",
      "primary": true,
      "person_id": "~{\"name\": \"Mansell\"}",
      "organization_id": null
    }
  ],
  "related_bills": [],
  "versions": [
    {
      "note": "Current version",
      "links": [
        {
          "url": "http://billstatus.ls.state.ms.us/documents/2026/html/HB/1400-1499/HB1418IN.htm",
          "media_type": "text/html"
        },
        {
          "url": "http://billstatus.ls.state.ms.us/documents/2026/pdf/HB/1400-1499/HB1418IN.pdf",
          "media_type": "application/pdf"
        }
      ],
      "date": "",
      "classification": ""
    }
  ],
  "documents": [],
  "citations": [],
  "sources": [
    {
      "url": "https://billstatus.ls.state.ms.us/documents/2026/pdf/HB/1400-1499/HB1418IN.pdf",
      "note": ""
    },
    {
      "url": "http://billstatus.ls.state.ms.us/2026/pdf/House_authors/Mansell.xml",
      "note": ""
    },
    {
      "url": "https://billstatus.ls.state.ms.us/2026/pdf/history/HB/HB1418.xml",
      "note": ""
    }
  ],
  "extras": {
    "summary": "AN ACT TO AMEND SECTION 43-13-117, MISSISSIPPI CODE OF 1972, TO PROVIDE THAT THE DIVISION OF MEDICAID SHALL REIMBURSE FOR VAGUS NERVE STIMULATION (VNS) SURGICAL IMPLANT PROCEDURES PERFORMED IN HOSPITALS ON AN OUTPATIENT BASIS AND IN AMBULATORY SURGICAL FACILITIES AND TO PRESCRIBE THE RATES OF REIMBURSEMENT; TO PROVIDE THAT CONTRACTS ENTERED INTO OR RENEWED ON OR AFTER THE EFFECTIVE DATE OF THIS ACT BETWEEN THE DIVISION AND A MANAGED CARE ORGANIZATION MUST CONTAIN A REQUIREMENT THAT THE MANAGED CARE ORGANIZATION COMPLY WITH PROVISION REGARDING REIMBURSEMENT RATES FOR VNS SURGICAL IMPLANT PROCEDURES FOR FEE-FOR-SERVICE PROVIDERS; AND FOR RELATED PURPOSES."
  },
  "jurisdiction": {
    "id": "ocd-jurisdiction/country:us/state:ms/government",
    "name": "Mississippi",
    "classification": "state",
    "division_id": "ocd-division/country:us/state:ms"
  },
  "_processing": {
    "logs_latest_update": "2026-07-13T06:03:59Z",
    "text_extraction_latest_update": "2026-07-13T07:41:15.347297Z"
  }
}